avl_range_tree/__init__.py
avl_range_tree/avl_tree.py
avl_range_tree-0.4.0.dist-info/LICENSE
avl_range_tree-0.4.0.dist-info/METADATA
avl_range_tree-0.4.0.dist-info/WHEEL
avl_range_tree-0.4.0.dist-info/RECORD
