Metadata-Version: 2.1
Name: avl_range_tree
Version: 0.4.0
Summary: Augmented AVL tree to index and search intervals.
Home-page: https://github.com/mcoira/python-range-tree
Author: Mikel
Requires-Python: >=3.9,<4.0
Classifier: Programming Language :: Python :: 3
Classifier: Programming Language :: Python :: 3.9
Classifier: Programming Language :: Python :: 3.10
Classifier: Programming Language :: Python :: 3.11
Classifier: Programming Language :: Python :: 3.12
Project-URL: Repository, https://github.com/mcoira/python-range-tree
